kss/util/__init__.py
kss/util/command.py
kss/util/contract.py
kss/util/jsonreader.py
kss/util/strings.py
kss_pyutil-1.1.0.dist-info/LICENSE
kss_pyutil-1.1.0.dist-info/METADATA
kss_pyutil-1.1.0.dist-info/WHEEL
kss_pyutil-1.1.0.dist-info/top_level.txt
kss_pyutil-1.1.0.dist-info/RECORD
