Metadata-Version: 2.1
Name: kss-pyutil
Version: 1.1.0
Summary: General Python utilities
Home-page: https://github.com/klassen-software-solutions/pyutil
Author: Steven W. Klassen
Author-email: klassens@acm.org
License: MIT License
Platform: UNKNOWN
Classifier: Programming Language :: Python :: 3
Classifier: License :: OSI Approved :: MIT License
Classifier: Operating System :: OS Independent
Requires-Python: >=3.7
Requires-Dist: requests
